{
  "openapi": "3.0.1",
  "info": {
    "title": "API",
    "version": "1.0"
  },
  "paths": {
    "/Authentication": {
      "post": {
        "tags": [
          "Authentication"
        ],
        "requestBody": {
          "content": {
            "application/json": {
              "schema": {
                "$ref": "#/components/schemas/AuthenticationRequest"
              }
            },
            "text/json": {
              "schema": {
                "$ref": "#/components/schemas/AuthenticationRequest"
              }
            },
            "application/*+json": {
              "schema": {
                "$ref": "#/components/schemas/AuthenticationRequest"
              }
            }
          }
        },
        "responses": {
          "200": {
            "description": "OK"
          }
        }
      }
    },
    "/Country/List": {
      "get": {
        "tags": [
          "Country"
        ],
        "responses": {
          "200": {
            "description": "OK"
          }
        }
      }
    },
    "/CustomField": {
      "post": {
        "tags": [
          "CustomField"
        ],
        "requestBody": {
          "content": {
            "application/json": {
              "schema": {
                "$ref": "#/components/schemas/CustomField"
              }
            },
            "text/json": {
              "schema": {
                "$ref": "#/components/schemas/CustomField"
              }
            },
            "application/*+json": {
              "schema": {
                "$ref": "#/components/schemas/CustomField"
              }
            }
          }
        },
        "responses": {
          "200": {
            "description": "OK"
          }
        }
      },
      "put": {
        "tags": [
          "CustomField"
        ],
        "requestBody": {
          "content": {
            "application/json": {
              "schema": {
                "$ref": "#/components/schemas/CustomField"
              }
            },
            "text/json": {
              "schema": {
                "$ref": "#/components/schemas/CustomField"
              }
            },
            "application/*+json": {
              "schema": {
                "$ref": "#/components/schemas/CustomField"
              }
            }
          }
        },
        "responses": {
          "200": {
            "description": "OK"
          }
        }
      }
    },
    "/Report/CountrySupplierReport": {
      "get": {
        "tags": [
          "Report"
        ],
        "responses": {
          "200": {
            "description": "OK"
          }
        }
      }
    },
    "/Report/CountryServiceReport": {
      "get": {
        "tags": [
          "Report"
        ],
        "responses": {
          "200": {
            "description": "OK"
          }
        }
      }
    },
    "/Service": {
      "post": {
        "tags": [
          "Service"
        ],
        "requestBody": {
          "content": {
            "application/json": {
              "schema": {
                "$ref": "#/components/schemas/Service"
              }
            },
            "text/json": {
              "schema": {
                "$ref": "#/components/schemas/Service"
              }
            },
            "application/*+json": {
              "schema": {
                "$ref": "#/components/schemas/Service"
              }
            }
          }
        },
        "responses": {
          "200": {
            "description": "OK"
          }
        }
      },
      "put": {
        "tags": [
          "Service"
        ],
        "requestBody": {
          "content": {
            "application/json": {
              "schema": {
                "$ref": "#/components/schemas/Service"
              }
            },
            "text/json": {
              "schema": {
                "$ref": "#/components/schemas/Service"
              }
            },
            "application/*+json": {
              "schema": {
                "$ref": "#/components/schemas/Service"
              }
            }
          }
        },
        "responses": {
          "200": {
            "description": "OK"
          }
        }
      }
    },
    "/Supplier/List": {
      "get": {
        "tags": [
          "Supplier"
        ],
        "responses": {
          "200": {
            "description": "OK"
          }
        }
      }
    },
    "/Supplier": {
      "post": {
        "tags": [
          "Supplier"
        ],
        "requestBody": {
          "content": {
            "application/json": {
              "schema": {
                "$ref": "#/components/schemas/Supplier"
              }
            },
            "text/json": {
              "schema": {
                "$ref": "#/components/schemas/Supplier"
              }
            },
            "application/*+json": {
              "schema": {
                "$ref": "#/components/schemas/Supplier"
              }
            }
          }
        },
        "responses": {
          "200": {
            "description": "OK"
          }
        }
      },
      "put": {
        "tags": [
          "Supplier"
        ],
        "requestBody": {
          "content": {
            "application/json": {
              "schema": {
                "$ref": "#/components/schemas/Supplier"
              }
            },
            "text/json": {
              "schema": {
                "$ref": "#/components/schemas/Supplier"
              }
            },
            "application/*+json": {
              "schema": {
                "$ref": "#/components/schemas/Supplier"
              }
            }
          }
        },
        "responses": {
          "200": {
            "description": "OK"
          }
        }
      }
    }
  },
  "components": {
    "schemas": {
      "AuthenticationRequest": {
        "required": [
          "password",
          "username"
        ],
        "type": "object",
        "properties": {
          "username": {
            "type": "string",
            "nullable": true
          },
          "password": {
            "type": "string",
            "nullable": true
          }
        },
        "additionalProperties": false
      },
      "Country": {
        "required": [
          "code",
          "name"
        ],
        "type": "object",
        "properties": {
          "id": {
            "type": "integer",
            "format": "int32"
          },
          "code": {
            "type": "string",
            "nullable": true
          },
          "name": {
            "type": "string",
            "nullable": true
          }
        },
        "additionalProperties": false
      },
      "CustomField": {
        "required": [
          "name",
          "value"
        ],
        "type": "object",
        "properties": {
          "id": {
            "type": "integer",
            "format": "int32"
          },
          "supplierId": {
            "type": "integer",
            "format": "int32"
          },
          "name": {
            "type": "string",
            "nullable": true
          },
          "value": {
            "type": "string",
            "nullable": true
          }
        },
        "additionalProperties": false
      },
      "Service": {
        "required": [
          "name"
        ],
        "type": "object",
        "properties": {
          "id": {
            "type": "integer",
            "format": "int32"
          },
          "supplierId": {
            "type": "integer",
            "format": "int32"
          },
          "name": {
            "type": "string",
            "nullable": true
          },
          "hourValue": {
            "type": "number",
            "format": "double"
          },
          "countries": {
            "type": "array",
            "items": {
              "$ref": "#/components/schemas/Country"
            },
            "nullable": true
          }
        },
        "additionalProperties": false
      },
      "Supplier": {
        "required": [
          "email",
          "name"
        ],
        "type": "object",
        "properties": {
          "id": {
            "type": "integer",
            "format": "int32"
          },
          "nit": {
            "type": "integer",
            "format": "int32"
          },
          "name": {
            "type": "string",
            "nullable": true
          },
          "email": {
            "type": "string",
            "nullable": true
          },
          "services": {
            "type": "array",
            "items": {
              "$ref": "#/components/schemas/Service"
            },
            "nullable": true
          },
          "customFields": {
            "type": "array",
            "items": {
              "$ref": "#/components/schemas/CustomField"
            },
            "nullable": true
          }
        },
        "additionalProperties": false
      }
    }
  }
}